tokio_memq/__init__.py
tokio_memq/tokio_memq.abi3.so
tokio_memq_python-0.1.3.dist-info/METADATA
tokio_memq_python-0.1.3.dist-info/WHEEL
tokio_memq_python-0.1.3.dist-info/RECORD
