Metadata-Version: 2.4
Name: tokio-memq-python
Version: 0.1.3
Summary: Python bindings for tokio-memq
Requires-Python: >=3.8
